dash_console_filter_plugin/__init__.py
dash_console_filter_plugin-0.1.0.dist-info/licenses/LICENSE
dash_console_filter_plugin-0.1.0.dist-info/METADATA
dash_console_filter_plugin-0.1.0.dist-info/WHEEL
dash_console_filter_plugin-0.1.0.dist-info/top_level.txt
dash_console_filter_plugin-0.1.0.dist-info/RECORD
