Metadata-Version: 2.4
Name: dash-console-filter-plugin
Version: 0.1.0
Summary: A plugin to filter the error messages in the console of the browser for Dash applications using Dash Hooks.
Home-page: https://github.com/CNFeffery/dash-console-filter-plugin
Author: CNFeffery
Author-email: fefferypzy@gmail.com
License-File: LICENSE
Requires-Dist: dash>=3.1.1
Dynamic: author
Dynamic: author-email
Dynamic: description
Dynamic: description-content-type
Dynamic: home-page
Dynamic: license-file
Dynamic: requires-dist
Dynamic: summary
